[
  {
    "url": "https://en.wikipedia.org/wiki/Anscombe%27s_quartet",
    "dataset": 1,
    "x": 10,
    "y": 8.04
  },
  {
    "dataset": 1,
    "x": 8,
    "y": 6.95
  },
  {
    "dataset": 1,
    "x": 13,
    "y": 7.58
  },
  {
    "dataset": 1,
    "x": 9,
    "y": 8.81
  },
  {
    "dataset": 1,
    "x": 11,
    "y": 8.33
  },
  {
    "dataset": 1,
    "x": 14,
    "y": 9.96
  },
  {
    "dataset": 1,
    "x": 6,
    "y": 7.24
  },
  {
    "dataset": 1,
    "x": 4,
    "y": 4.26
  },
  {
    "dataset": 1,
    "x": 12,
    "y": 10.84
  },
  {
    "dataset": 1,
    "x": 7,
    "y": 4.82
  },
  {
    "dataset": 1,
    "x": 5,
    "y": 5.68
  },
  {
    "dataset": 2,
    "x": 10,
    "y": 9.14
  },
  {
    "dataset": 2,
    "x": 8,
    "y": 8.14
  },
  {
    "dataset": 2,
    "x": 13,
    "y": 8.74
  },
  {
    "dataset": 2,
    "x": 9,
    "y": 8.77
  },
  {
    "dataset": 2,
    "x": 11,
    "y": 9.26
  },
  {
    "dataset": 2,
    "x": 14,
    "y": 8.1
  },
  {
    "dataset": 2,
    "x": 6,
    "y": 6.13
  },
  {
    "dataset": 2,
    "x": 4,
    "y": 3.1
  },
  {
    "dataset": 2,
    "x": 12,
    "y": 9.13
  },
  {
    "dataset": 2,
    "x": 7,
    "y": 7.26
  },
  {
    "dataset": 2,
    "x": 5,
    "y": 4.74
  },
  {
    "dataset": 3,
    "x": 10,
    "y": 7.46
  },
  {
    "dataset": 3,
    "x": 8,
    "y": 6.77
  },
  {
    "dataset": 3,
    "x": 13,
    "y": 12.74
  },
  {
    "dataset": 3,
    "x": 9,
    "y": 7.11
  },
  {
    "dataset": 3,
    "x": 11,
    "y": 7.81
  },
  {
    "dataset": 3,
    "x": 14,
    "y": 8.84
  },
  {
    "dataset": 3,
    "x": 6,
    "y": 6.08
  },
  {
    "dataset": 3,
    "x": 4,
    "y": 5.39
  },
  {
    "dataset": 3,
    "x": 12,
    "y": 8.15
  },
  {
    "dataset": 3,
    "x": 7,
    "y": 6.42
  },
  {
    "dataset": 3,
    "x": 5,
    "y": 5.73
  },
  {
    "dataset": 4,
    "x": 8,
    "y": 6.58
  },
  {
    "dataset": 4,
    "x": 8,
    "y": 5.76
  },
  {
    "dataset": 4,
    "x": 8,
    "y": 7.71
  },
  {
    "dataset": 4,
    "x": 8,
    "y": 8.84
  },
  {
    "dataset": 4,
    "x": 8,
    "y": 8.47
  },
  {
    "dataset": 4,
    "x": 8,
    "y": 7.04
  },
  {
    "dataset": 4,
    "x": 8,
    "y": 5.25
  },
  {
    "dataset": 4,
    "x": 19,
    "y": 12.5
  },
  {
    "dataset": 4,
    "x": 8,
    "y": 5.56
  },
  {
    "dataset": 4,
    "x": 8,
    "y": 7.91
  },
  {
    "dataset": 4,
    "x": 8,
    "y": 6.89
  }
]
